asyncrequester/__init__.py
asyncrequester-0.1.3.dist-info/LICENCE.txt
asyncrequester-0.1.3.dist-info/METADATA
asyncrequester-0.1.3.dist-info/WHEEL
asyncrequester-0.1.3.dist-info/top_level.txt
asyncrequester-0.1.3.dist-info/RECORD
