Metadata-Version: 2.1
Name: asyncrequester
Version: 0.1.3
Summary: Basic async requester
Home-page: https://github.com/hamitaksln/asyncrequester
Author: Abdulhamit Akaslan
Author-email: hamtaksln@gmail.com
License: MIT
Keywords: async
Platform: UNKNOWN
Classifier: Development Status :: 5 - Production/Stable
Classifier: Intended Audience :: Education
Classifier: Operating System :: Microsoft :: Windows :: Windows 10
Classifier: License :: OSI Approved :: MIT License
Classifier: Programming Language :: Python :: 3
Requires-Dist: grequests
